bmi_ryang/bmi.py
bmi_ryang-0.0.0.1.dist-info/METADATA
bmi_ryang-0.0.0.1.dist-info/WHEEL
bmi_ryang-0.0.0.1.dist-info/top_level.txt
bmi_ryang-0.0.0.1.dist-info/RECORD
