Metadata-Version: 2.1
Name: bmi-ryang
Version: 0.0.0.1
Summary: My BMI Package
Home-page: https://blog.naver.com/hwang7531
Author: Beopryang Hwang
License: MIT
Platform: UNKNOWN
Requires-Python: >=3
